shorten_func/__init__.py
shorten_func-0.1.1.dist-info/LICENSE
shorten_func-0.1.1.dist-info/METADATA
shorten_func-0.1.1.dist-info/WHEEL
shorten_func-0.1.1.dist-info/top_level.txt
shorten_func-0.1.1.dist-info/RECORD
