Metadata-Version: 2.1
Name: shorten-func
Version: 0.1.1
Summary: Reduce to pass the same parameters multiple times when calling a function multiple times
Home-page: https://github.com/Yellorn/shorten-func
Author: Hoang Yell
Author-email: ngohoang.yell@gmail.com
License: UNKNOWN
Platform: UNKNOWN
Classifier: Programming Language :: Python :: 3
Classifier: License :: OSI Approved :: MIT License
Classifier: Operating System :: OS Independent
Requires-Python: >=3.0
